examples/basic_dro_fail/dro.v
// Adapted from TimEx generated files for vcd_assert testing
`define begin_time 8
`timescale 1ps/100fs
module basic_dro (set, reset, out);

// Define inputs
input set, reset;

// Define outputs
output out;
wire out;

// Internal output variables
reg internal_out;
assign out = internal_out;

// State
integer state;

// Internal state variables
wire internal_state_0,
     internal_state_1;

assign internal_state_0 = state === 0;
assign internal_state_1 = state === 1;

specify
    // Output delays spec params
    specparam delay_state1_reset_out = 5.5;

    // Critical timing spec params
    specparam ct_state0_set_reset    = 2.5;
    specparam ct_state0_reset_set    = 2.5;
    specparam ct_state1_set_reset    = 2.5;

    // Define output delays
    if (internal_state_1) (reset => out) = delay_state1_reset_out;

    // Define critical timing assertions
    $hold( posedge set &&& internal_state_0, reset, ct_state0_set_reset);
    $hold( negedge set &&& internal_state_0, reset, ct_state0_set_reset);

    $hold( posedge set &&& internal_state_1, reset, ct_state1_set_reset);
    $hold( negedge set &&& internal_state_1, reset, ct_state1_set_reset);

    $hold( posedge reset &&& internal_state_0, set, ct_state0_reset_set);
    $hold( negedge reset &&& internal_state_0, set, ct_state0_reset_set);

endspecify

initial begin
    state = 1'bX;
    internal_out = 0;
    #`begin_time state = 0;
end

always @(posedge set or negedge set)
case (state)
    0: begin 
        state = 1;
    end
endcase

always @(posedge reset or negedge reset)
case (state)
    1: begin
        internal_out = !internal_out;
        state = 0;
    end
endcase

endmodule

examples/basic_dro_fail/tb_dro.v
`timescale 1ps/100fs
module tb_basic_dro;
    reg set = 0;
    reg reset = 0;

    initial begin
        $sdf_annotate("../dro.sdf", tb_basic_dro);
        $dumpfile("tb_basic_dro.vcd");
        $dumpvars;

        #10 set = !set;
        #10 set = !set;
        #2 reset = !reset; // Timing violation
        #10 reset = !reset;
    end

    initial begin
        $display("\t\ttime,\tset,\treset,\tout");
        $monitor("\t\t%0t,\t%b,\t%b,\t%b",$realtime,set,reset,out);
    end

    basic_dro DUT (set, reset, out);

    initial #50 $finish;
endmodule

examples/basic_dro_fail/cver_out/tb_basic_dro.vcd
$date
    Tue Jul 31 21:39:58 2018
$end
$version
    GPLCVER_2.12a of 05/16/07
$end
$timescale
    100 fs
$end
$scope module tb_basic_dro $end
$var wire       1 !    out $end
$var reg       1 "    reset $end
$var reg       1 #    set $end
$scope module DUT $end
$var reg       1 $    internal_out $end
$var wire       1 %    internal_state_0 $end
$var wire       1 &    internal_state_1 $end
$var wire       1 '    out $end
$var wire       1 (    reset $end
$var wire       1 )    set $end
$var integer      32 *    state [31:0] $end
$upscope $end
$upscope $end
$enddefinitions $end
#0
$dumpvars
x!
0"
0#
0$
x%
x&
x'
0(
0)
b0x *
$end
#55
0!
0'
#80
1%
0&
b0 *
#100
0%
1&
b1 *
1)
1#
#200
0)
0#
#220
1%
0&
b0 *
1$
1(
1"
#275
1!
1'
#320
0(
0"
